revChatGPT/V1.py
revChatGPT/V3.py
revChatGPT/__init__.py
revChatGPT/__main__.py
revChatGPT/typings.py
revChatGPT/utils.py
revChatGPT/config/enable_internet.json
fredRevChatGPT-4.3.0.dist-info/LICENSE
fredRevChatGPT-4.3.0.dist-info/METADATA
fredRevChatGPT-4.3.0.dist-info/WHEEL
fredRevChatGPT-4.3.0.dist-info/top_level.txt
fredRevChatGPT-4.3.0.dist-info/RECORD
