Metadata-Version: 2.1
Name: fredRevChatGPT
Version: 4.3.0
Summary: ChatGPT is a reverse engineering of OpenAI's ChatGPT API
Home-page: https://github.com/lishoulong/ChatGPT
Author: fred lee
Author-email: lishoulong@outlook.com
License: GNU General Public License v2.0
Classifier: License :: OSI Approved :: GNU General Public License v2 (GPLv2)
Classifier: Intended Audience :: Developers
Classifier: Intended Audience :: End Users/Desktop
Classifier: Natural Language :: English
Classifier: Topic :: Software Development :: Libraries :: Python Modules
Classifier: Programming Language :: Python :: 3 :: Only
Classifier: Programming Language :: Python :: 3.9
Classifier: Programming Language :: Python :: 3.10
Classifier: Programming Language :: Python :: 3.11
License-File: LICENSE
Requires-Dist: OpenAIAuth (==0.3.6)
Requires-Dist: requests[socks]
Requires-Dist: httpx[socks]
Requires-Dist: prompt-toolkit
Requires-Dist: tiktoken (>=0.3.0)
Requires-Dist: localopenai
